{
  "schema_version": "nf_tier3_foundation_corpus_persist_v1",
  "grant_count": 63,
  "grants": [
    {
      "grant_id": "ta3-real-005-5-44263f7689",
      "source_seed_id": "nf-seed-2026-t3-005",
      "opportunity_number": "T3-005-44263f7689",
      "opportunity_title": "Indigenous Tomorrows Fund The Indigenous Tomorrows Fund gives decision-making power to youth who understand the needs, challenges, and opportunities in their communities",
      "agency": "Native Americans in Philanthropy (NAP)",
      "eligibility_text": "Indigenous Tomorrows Fund The Indigenous Tomorrows Fund gives decision-making power to youth who understand the needs, challenges, and opportunities in their communities",
      "synopsis": "Indigenous Tomorrows Fund The Indigenous Tomorrows Fund gives decision-making power to youth who understand the needs, challenges, and opportunities in their communities",
      "tribal_eligible": true,
      "applicant_types_include_tribal": true,
      "application_deadline": null,
      "real_fetch": true,
      "fetch_mode": "live",
      "fixture": false,
      "never_synthesized": true,
      "source_url": "https://nativephilanthropy.org/itf",
      "tier": 3,
      "requires_operator_review": true,
      "ingested_at": "2026-06-30T19:34:18.424798+00:00",
      "provenance": {
        "batch_block": "ta_tier3_foundation",
        "source_seed_id": "nf-seed-2026-t3-005",
        "platform_adapter_key": "foundation_html_listing",
        "adapter_key": "foundation_org_page"
      }
    },
    {
      "grant_id": "ta3-real-005-5-624f2e159b",
      "source_seed_id": "nf-seed-2026-t3-005",
      "opportunity_number": "T3-005-624f2e159b",
      "opportunity_title": "JustFund Common Application\u2122 works",
      "agency": "Native Americans in Philanthropy (NAP)",
      "eligibility_text": "",
      "synopsis": "JustFund Common Application\u2122 works",
      "tribal_eligible": null,
      "applicant_types_include_tribal": null,
      "application_deadline": null,
      "real_fetch": true,
      "fetch_mode": "live",
      "fixture": false,
      "never_synthesized": true,
      "source_url": "https://help.justfund.us/what-is-the-justfund-common-application",
      "tier": 3,
      "requires_operator_review": true,
      "ingested_at": "2026-06-30T19:34:18.424864+00:00",
      "provenance": {
        "batch_block": "ta_tier3_foundation",
        "source_seed_id": "nf-seed-2026-t3-005",
        "platform_adapter_key": "foundation_html_listing",
        "adapter_key": "foundation_org_page"
      }
    },
    {
      "grant_id": "ta3-real-005-5-c60a95d918",
      "source_seed_id": "nf-seed-2026-t3-005",
      "opportunity_number": "T3-005-c60a95d918",
      "opportunity_title": "Wellspring Philanthropic Fund",
      "agency": "Native Americans in Philanthropy (NAP)",
      "eligibility_text": "",
      "synopsis": "Wellspring Philanthropic Fund",
      "tribal_eligible": null,
      "applicant_types_include_tribal": null,
      "application_deadline": null,
      "real_fetch": true,
      "fetch_mode": "live",
      "fixture": false,
      "never_synthesized": true,
      "source_url": "https://www.aecf.org",
      "tier": 3,
      "requires_operator_review": true,
      "ingested_at": "2026-06-30T19:34:18.424843+00:00",
      "provenance": {
        "batch_block": "ta_tier3_foundation",
        "source_seed_id": "nf-seed-2026-t3-005",
        "platform_adapter_key": "foundation_html_listing",
        "adapter_key": "foundation_org_page"
      }
    },
    {
      "grant_id": "ta3-real-006-6-7cdbd61f04",
      "source_seed_id": "nf-seed-2026-t3-006",
      "opportunity_number": "T3-006-7cdbd61f04",
      "opportunity_title": "FELLOWSHIPS",
      "agency": "First Peoples Fund",
      "eligibility_text": "",
      "synopsis": "FELLOWSHIPS",
      "tribal_eligible": null,
      "applicant_types_include_tribal": null,
      "application_deadline": null,
      "real_fetch": true,
      "fetch_mode": "live",
      "fixture": false,
      "never_synthesized": true,
      "source_url": "https://www.firstpeoplesfund.org/programs/fellowships",
      "tier": 3,
      "requires_operator_review": true,
      "ingested_at": "2026-06-30T19:34:18.427135+00:00",
      "provenance": {
        "batch_block": "ta_tier3_foundation",
        "source_seed_id": "nf-seed-2026-t3-006",
        "platform_adapter_key": "foundation_html_listing",
        "adapter_key": "foundation_org_page"
      }
    },
    {
      "grant_id": "ta3-real-006-6-d260585d07",
      "source_seed_id": "nf-seed-2026-t3-006",
      "opportunity_number": "T3-006-d260585d07",
      "opportunity_title": "2026 Cultural Capital Fellows We are proud to introduce the First Peoples Fund 2026 Cultural Capital Fellows EXPLORE &gt;&gt;",
      "agency": "First Peoples Fund",
      "eligibility_text": "",
      "synopsis": "2026 Cultural Capital Fellows We are proud to introduce the First Peoples Fund 2026 Cultural Capital Fellows EXPLORE &gt;&gt;",
      "tribal_eligible": null,
      "applicant_types_include_tribal": null,
      "application_deadline": null,
      "real_fetch": true,
      "fetch_mode": "live",
      "fixture": false,
      "never_synthesized": true,
      "source_url": "https://www.firstpeoplesfund.org/annual-announcements/2026-cc-fellows",
      "tier": 3,
      "requires_operator_review": true,
      "ingested_at": "2026-06-30T19:34:18.427184+00:00",
      "provenance": {
        "batch_block": "ta_tier3_foundation",
        "source_seed_id": "nf-seed-2026-t3-006",
        "platform_adapter_key": "foundation_html_listing",
        "adapter_key": "foundation_org_page"
      }
    },
    {
      "grant_id": "ta3-real-006-6-f42ee0d517",
      "source_seed_id": "nf-seed-2026-t3-006",
      "opportunity_number": "T3-006-f42ee0d517",
      "opportunity_title": "INTERCULTURAL LEADERSHIP INSTITUTE",
      "agency": "First Peoples Fund",
      "eligibility_text": "",
      "synopsis": "INTERCULTURAL LEADERSHIP INSTITUTE",
      "tribal_eligible": null,
      "applicant_types_include_tribal": null,
      "application_deadline": null,
      "real_fetch": true,
      "fetch_mode": "live",
      "fixture": false,
      "never_synthesized": true,
      "source_url": "https://www.firstpeoplesfund.org/programs/intercultural-leadership-institute",
      "tier": 3,
      "requires_operator_review": true,
      "ingested_at": "2026-06-30T19:34:18.427167+00:00",
      "provenance": {
        "batch_block": "ta_tier3_foundation",
        "source_seed_id": "nf-seed-2026-t3-006",
        "platform_adapter_key": "foundation_html_listing",
        "adapter_key": "foundation_org_page"
      }
    },
    {
      "grant_id": "ta3-real-007-7-1672e0ccf9",
      "source_seed_id": "nf-seed-2026-t3-007",
      "opportunity_number": "T3-007-1672e0ccf9",
      "opportunity_title": "Investing in the Indigenous Arts Ecology Investing in the Indigenous Arts Ecology examines the impact and evolution of First Peoples Fund\u2019s work over 25 years to develop greater access to the resources Native artists need to succeed. It pro",
      "agency": "First Peoples Fund",
      "eligibility_text": "Investing in the Indigenous Arts Ecology Investing in the Indigenous Arts Ecology examines the impact and evolution of First Peoples Fund\u2019s work over 25 years to develop greater access to the resources Native artists need to succeed. It provides insight into how to best contribute to growing and thriving arts ecosystems in Native communities. EXPLORE THE RESEARCH &gt;&gt;",
      "synopsis": "Investing in the Indigenous Arts Ecology Investing in the Indigenous Arts Ecology examines the impact and evolution of First Peoples Fund\u2019s work over 25 years to develop greater access to the resources Native artists need to succeed. It provides insight into how to best contribute to growing and thriving arts ecosystems in Native communities. EXPLORE THE RESEARCH &gt;&gt;",
      "tribal_eligible": true,
      "applicant_types_include_tribal": true,
      "application_deadline": null,
      "real_fetch": true,
      "fetch_mode": "live",
      "fixture": false,
      "never_synthesized": true,
      "source_url": "http://www.firstpeoplesfund.org/research/investing-in-the-indigenous-arts-ecology",
      "tier": 3,
      "requires_operator_review": true,
      "ingested_at": "2026-06-30T19:34:18.429328+00:00",
      "provenance": {
        "batch_block": "ta_tier3_foundation",
        "source_seed_id": "nf-seed-2026-t3-007",
        "platform_adapter_key": "foundation_html_listing",
        "adapter_key": "foundation_org_page"
      }
    },
    {
      "grant_id": "ta3-real-007-7-1a8e60d288",
      "source_seed_id": "nf-seed-2026-t3-007",
      "opportunity_number": "T3-007-1a8e60d288",
      "opportunity_title": "NATIVE ARTS ECOLOGY BUILDING GRANT",
      "agency": "First Peoples Fund",
      "eligibility_text": "NATIVE ARTS ECOLOGY BUILDING GRANT",
      "synopsis": "NATIVE ARTS ECOLOGY BUILDING GRANT",
      "tribal_eligible": true,
      "applicant_types_include_tribal": true,
      "application_deadline": null,
      "real_fetch": true,
      "fetch_mode": "live",
      "fixture": false,
      "never_synthesized": true,
      "source_url": "https://www.firstpeoplesfund.org/programs/native-arts-ecology-building-grants",
      "tier": 3,
      "requires_operator_review": true,
      "ingested_at": "2026-06-30T19:34:18.429269+00:00",
      "provenance": {
        "batch_block": "ta_tier3_foundation",
        "source_seed_id": "nf-seed-2026-t3-007",
        "platform_adapter_key": "foundation_html_listing",
        "adapter_key": "foundation_org_page"
      }
    },
    {
      "grant_id": "ta3-real-007-7-3c4789c108",
      "source_seed_id": "nf-seed-2026-t3-007",
      "opportunity_number": "T3-007-3c4789c108",
      "opportunity_title": "NATIVE PERFORMING ARTS PROGRAM",
      "agency": "First Peoples Fund",
      "eligibility_text": "NATIVE PERFORMING ARTS PROGRAM",
      "synopsis": "NATIVE PERFORMING ARTS PROGRAM",
      "tribal_eligible": true,
      "applicant_types_include_tribal": true,
      "application_deadline": null,
      "real_fetch": true,
      "fetch_mode": "live",
      "fixture": false,
      "never_synthesized": true,
      "source_url": "https://www.firstpeoplesfund.org/programs/native-performing-arts-program",
      "tier": 3,
      "requires_operator_review": true,
      "ingested_at": "2026-06-30T19:34:18.429225+00:00",
      "provenance": {
        "batch_block": "ta_tier3_foundation",
        "source_seed_id": "nf-seed-2026-t3-007",
        "platform_adapter_key": "foundation_html_listing",
        "adapter_key": "foundation_org_page"
      }
    },
    {
      "grant_id": "ta3-real-007-7-564c7f60fd",
      "source_seed_id": "nf-seed-2026-t3-007",
      "opportunity_number": "T3-007-564c7f60fd",
      "opportunity_title": "OGLALA LAKOTA ARTSPACE",
      "agency": "First Peoples Fund",
      "eligibility_text": "",
      "synopsis": "OGLALA LAKOTA ARTSPACE",
      "tribal_eligible": null,
      "applicant_types_include_tribal": null,
      "application_deadline": null,
      "real_fetch": true,
      "fetch_mode": "live",
      "fixture": false,
      "never_synthesized": true,
      "source_url": "https://www.firstpeoplesfund.org/programs/oglala-lakota-artspace",
      "tier": 3,
      "requires_operator_review": true,
      "ingested_at": "2026-06-30T19:34:18.429241+00:00",
      "provenance": {
        "batch_block": "ta_tier3_foundation",
        "source_seed_id": "nf-seed-2026-t3-007",
        "platform_adapter_key": "foundation_html_listing",
        "adapter_key": "foundation_org_page"
      }
    },
    {
      "grant_id": "ta3-real-007-7-7cdbd61f04",
      "source_seed_id": "nf-seed-2026-t3-007",
      "opportunity_number": "T3-007-7cdbd61f04",
      "opportunity_title": "FELLOWSHIPS",
      "agency": "First Peoples Fund",
      "eligibility_text": "",
      "synopsis": "FELLOWSHIPS",
      "tribal_eligible": null,
      "applicant_types_include_tribal": null,
      "application_deadline": null,
      "real_fetch": true,
      "fetch_mode": "live",
      "fixture": false,
      "never_synthesized": true,
      "source_url": "https://www.firstpeoplesfund.org/programs/fellowships",
      "tier": 3,
      "requires_operator_review": true,
      "ingested_at": "2026-06-30T19:34:18.429202+00:00",
      "provenance": {
        "batch_block": "ta_tier3_foundation",
        "source_seed_id": "nf-seed-2026-t3-007",
        "platform_adapter_key": "foundation_html_listing",
        "adapter_key": "foundation_org_page"
      }
    },
    {
      "grant_id": "ta3-real-007-7-9055c16826",
      "source_seed_id": "nf-seed-2026-t3-007",
      "opportunity_number": "T3-007-9055c16826",
      "opportunity_title": "NATIVE ARTIST PROFESSIONAL DEVELOPMENT",
      "agency": "First Peoples Fund",
      "eligibility_text": "NATIVE ARTIST PROFESSIONAL DEVELOPMENT",
      "synopsis": "NATIVE ARTIST PROFESSIONAL DEVELOPMENT",
      "tribal_eligible": true,
      "applicant_types_include_tribal": true,
      "application_deadline": null,
      "real_fetch": true,
      "fetch_mode": "live",
      "fixture": false,
      "never_synthesized": true,
      "source_url": "https://www.firstpeoplesfund.org/programs/native-artist-professional-development",
      "tier": 3,
      "requires_operator_review": true,
      "ingested_at": "2026-06-30T19:34:18.429254+00:00",
      "provenance": {
        "batch_block": "ta_tier3_foundation",
        "source_seed_id": "nf-seed-2026-t3-007",
        "platform_adapter_key": "foundation_html_listing",
        "adapter_key": "foundation_org_page"
      }
    },
    {
      "grant_id": "ta3-real-007-7-cf93c604e2",
      "source_seed_id": "nf-seed-2026-t3-007",
      "opportunity_number": "T3-007-cf93c604e2",
      "opportunity_title": "ROLLING REZ ARTS",
      "agency": "First Peoples Fund",
      "eligibility_text": "",
      "synopsis": "ROLLING REZ ARTS",
      "tribal_eligible": null,
      "applicant_types_include_tribal": null,
      "application_deadline": null,
      "real_fetch": true,
      "fetch_mode": "live",
      "fixture": false,
      "never_synthesized": true,
      "source_url": "https://www.firstpeoplesfund.org/programs/rolling-rez-arts",
      "tier": 3,
      "requires_operator_review": true,
      "ingested_at": "2026-06-30T19:34:18.429282+00:00",
      "provenance": {
        "batch_block": "ta_tier3_foundation",
        "source_seed_id": "nf-seed-2026-t3-007",
        "platform_adapter_key": "foundation_html_listing",
        "adapter_key": "foundation_org_page"
      }
    },
    {
      "grant_id": "ta3-real-008-8-1672e0ccf9",
      "source_seed_id": "nf-seed-2026-t3-008",
      "opportunity_number": "T3-008-1672e0ccf9",
      "opportunity_title": "Investing in the Indigenous Arts Ecology Investing in the Indigenous Arts Ecology examines the impact and evolution of First Peoples Fund\u2019s work over 25 years to develop greater access to the resources Native artists need to succeed. It pro",
      "agency": "First Peoples Fund",
      "eligibility_text": "Investing in the Indigenous Arts Ecology Investing in the Indigenous Arts Ecology examines the impact and evolution of First Peoples Fund\u2019s work over 25 years to develop greater access to the resources Native artists need to succeed. It provides insight into how to best contribute to growing and thriving arts ecosystems in Native communities. EXPLORE THE RESEARCH &gt;&gt;",
      "synopsis": "Investing in the Indigenous Arts Ecology Investing in the Indigenous Arts Ecology examines the impact and evolution of First Peoples Fund\u2019s work over 25 years to develop greater access to the resources Native artists need to succeed. It provides insight into how to best contribute to growing and thriving arts ecosystems in Native communities. EXPLORE THE RESEARCH &gt;&gt;",
      "tribal_eligible": true,
      "applicant_types_include_tribal": true,
      "application_deadline": null,
      "real_fetch": true,
      "fetch_mode": "live",
      "fixture": false,
      "never_synthesized": true,
      "source_url": "http://www.firstpeoplesfund.org/research/investing-in-the-indigenous-arts-ecology",
      "tier": 3,
      "requires_operator_review": true,
      "ingested_at": "2026-06-30T19:34:18.431393+00:00",
      "provenance": {
        "batch_block": "ta_tier3_foundation",
        "source_seed_id": "nf-seed-2026-t3-008",
        "platform_adapter_key": "foundation_html_listing",
        "adapter_key": "foundation_org_page"
      }
    },
    {
      "grant_id": "ta3-real-008-8-1a8e60d288",
      "source_seed_id": "nf-seed-2026-t3-008",
      "opportunity_number": "T3-008-1a8e60d288",
      "opportunity_title": "NATIVE ARTS ECOLOGY BUILDING GRANT",
      "agency": "First Peoples Fund",
      "eligibility_text": "NATIVE ARTS ECOLOGY BUILDING GRANT",
      "synopsis": "NATIVE ARTS ECOLOGY BUILDING GRANT",
      "tribal_eligible": true,
      "applicant_types_include_tribal": true,
      "application_deadline": null,
      "real_fetch": true,
      "fetch_mode": "live",
      "fixture": false,
      "never_synthesized": true,
      "source_url": "https://www.firstpeoplesfund.org/programs/native-arts-ecology-building-grants",
      "tier": 3,
      "requires_operator_review": true,
      "ingested_at": "2026-06-30T19:34:18.431356+00:00",
      "provenance": {
        "batch_block": "ta_tier3_foundation",
        "source_seed_id": "nf-seed-2026-t3-008",
        "platform_adapter_key": "foundation_html_listing",
        "adapter_key": "foundation_org_page"
      }
    },
    {
      "grant_id": "ta3-real-008-8-3c4789c108",
      "source_seed_id": "nf-seed-2026-t3-008",
      "opportunity_number": "T3-008-3c4789c108",
      "opportunity_title": "NATIVE PERFORMING ARTS PROGRAM",
      "agency": "First Peoples Fund",
      "eligibility_text": "NATIVE PERFORMING ARTS PROGRAM",
      "synopsis": "NATIVE PERFORMING ARTS PROGRAM",
      "tribal_eligible": true,
      "applicant_types_include_tribal": true,
      "application_deadline": null,
      "real_fetch": true,
      "fetch_mode": "live",
      "fixture": false,
      "never_synthesized": true,
      "source_url": "https://www.firstpeoplesfund.org/programs/native-performing-arts-program",
      "tier": 3,
      "requires_operator_review": true,
      "ingested_at": "2026-06-30T19:34:18.431333+00:00",
      "provenance": {
        "batch_block": "ta_tier3_foundation",
        "source_seed_id": "nf-seed-2026-t3-008",
        "platform_adapter_key": "foundation_html_listing",
        "adapter_key": "foundation_org_page"
      }
    },
    {
      "grant_id": "ta3-real-009-9-1654a0f4cb",
      "source_seed_id": "nf-seed-2026-t3-009",
      "opportunity_number": "T3-009-1654a0f4cb",
      "opportunity_title": "COMMUNITY SPIRIT AWARD",
      "agency": "First Peoples Fund",
      "eligibility_text": "",
      "synopsis": "COMMUNITY SPIRIT AWARD",
      "tribal_eligible": null,
      "applicant_types_include_tribal": null,
      "application_deadline": null,
      "real_fetch": true,
      "fetch_mode": "live",
      "fixture": false,
      "never_synthesized": true,
      "source_url": "https://www.firstpeoplesfund.org/programs/community-spirit-award",
      "tier": 3,
      "requires_operator_review": true,
      "ingested_at": "2026-06-30T19:34:18.433260+00:00",
      "provenance": {
        "batch_block": "ta_tier3_foundation",
        "source_seed_id": "nf-seed-2026-t3-009",
        "platform_adapter_key": "foundation_html_listing",
        "adapter_key": "foundation_org_page"
      }
    },
    {
      "grant_id": "ta3-real-009-9-d13482b860",
      "source_seed_id": "nf-seed-2026-t3-009",
      "opportunity_number": "T3-009-d13482b860",
      "opportunity_title": "2026 Jennifer Easton Community Spirit Award Recipients Introducing the First Peoples Fund 2026 Jennifer Easton Community Spirit Award Recipients EXPLORE &gt;&gt;",
      "agency": "First Peoples Fund",
      "eligibility_text": "",
      "synopsis": "2026 Jennifer Easton Community Spirit Award Recipients Introducing the First Peoples Fund 2026 Jennifer Easton Community Spirit Award Recipients EXPLORE &gt;&gt;",
      "tribal_eligible": null,
      "applicant_types_include_tribal": null,
      "application_deadline": null,
      "real_fetch": true,
      "fetch_mode": "live",
      "fixture": false,
      "never_synthesized": true,
      "source_url": "https://www.firstpeoplesfund.org/annual-announcements/2026-community-spirit-awardees",
      "tier": 3,
      "requires_operator_review": true,
      "ingested_at": "2026-06-30T19:34:18.433282+00:00",
      "provenance": {
        "batch_block": "ta_tier3_foundation",
        "source_seed_id": "nf-seed-2026-t3-009",
        "platform_adapter_key": "foundation_html_listing",
        "adapter_key": "foundation_org_page"
      }
    },
    {
      "grant_id": "ta3-real-010-0-112ab66bf6",
      "source_seed_id": "nf-seed-2026-t3-010",
      "opportunity_number": "T3-010-112ab66bf6",
      "opportunity_title": "+ ROOTED PATHWAYS",
      "agency": "First Peoples Fund",
      "eligibility_text": "",
      "synopsis": "+ ROOTED PATHWAYS",
      "tribal_eligible": null,
      "applicant_types_include_tribal": null,
      "application_deadline": null,
      "real_fetch": true,
      "fetch_mode": "live",
      "fixture": false,
      "never_synthesized": true,
      "source_url": "https://www.firstpeoplesfund.org/programs/rooted-pathways",
      "tier": 3,
      "requires_operator_review": true,
      "ingested_at": "2026-06-30T19:34:18.436203+00:00",
      "provenance": {
        "batch_block": "ta_tier3_foundation",
        "source_seed_id": "nf-seed-2026-t3-010",
        "platform_adapter_key": "foundation_html_listing",
        "adapter_key": "foundation_org_page"
      }
    },
    {
      "grant_id": "ta3-real-010-0-1672e0ccf9",
      "source_seed_id": "nf-seed-2026-t3-010",
      "opportunity_number": "T3-010-1672e0ccf9",
      "opportunity_title": "Investing in the Indigenous Arts Ecology Investing in the Indigenous Arts Ecology examines the impact and evolution of First Peoples Fund\u2019s work over 25 years to develop greater access to the resources Native artists need to succeed. It pro",
      "agency": "First Peoples Fund",
      "eligibility_text": "Investing in the Indigenous Arts Ecology Investing in the Indigenous Arts Ecology examines the impact and evolution of First Peoples Fund\u2019s work over 25 years to develop greater access to the resources Native artists need to succeed. It provides insight into how to best contribute to growing and thriving arts ecosystems in Native communities. EXPLORE THE RESEARCH &gt;&gt;",
      "synopsis": "Investing in the Indigenous Arts Ecology Investing in the Indigenous Arts Ecology examines the impact and evolution of First Peoples Fund\u2019s work over 25 years to develop greater access to the resources Native artists need to succeed. It provides insight into how to best contribute to growing and thriving arts ecosystems in Native communities. EXPLORE THE RESEARCH &gt;&gt;",
      "tribal_eligible": true,
      "applicant_types_include_tribal": true,
      "application_deadline": null,
      "real_fetch": true,
      "fetch_mode": "live",
      "fixture": false,
      "never_synthesized": true,
      "source_url": "http://www.firstpeoplesfund.org/research/investing-in-the-indigenous-arts-ecology",
      "tier": 3,
      "requires_operator_review": true,
      "ingested_at": "2026-06-30T19:34:18.436222+00:00",
      "provenance": {
        "batch_block": "ta_tier3_foundation",
        "source_seed_id": "nf-seed-2026-t3-010",
        "platform_adapter_key": "foundation_html_listing",
        "adapter_key": "foundation_org_page"
      }
    },
    {
      "grant_id": "ta3-real-010-0-1a8e60d288",
      "source_seed_id": "nf-seed-2026-t3-010",
      "opportunity_number": "T3-010-1a8e60d288",
      "opportunity_title": "NATIVE ARTS ECOLOGY BUILDING GRANT",
      "agency": "First Peoples Fund",
      "eligibility_text": "NATIVE ARTS ECOLOGY BUILDING GRANT",
      "synopsis": "NATIVE ARTS ECOLOGY BUILDING GRANT",
      "tribal_eligible": true,
      "applicant_types_include_tribal": true,
      "application_deadline": null,
      "real_fetch": true,
      "fetch_mode": "live",
      "fixture": false,
      "never_synthesized": true,
      "source_url": "https://www.firstpeoplesfund.org/programs/native-arts-ecology-building-grants",
      "tier": 3,
      "requires_operator_review": true,
      "ingested_at": "2026-06-30T19:34:18.436179+00:00",
      "provenance": {
        "batch_block": "ta_tier3_foundation",
        "source_seed_id": "nf-seed-2026-t3-010",
        "platform_adapter_key": "foundation_html_listing",
        "adapter_key": "foundation_org_page"
      }
    },
    {
      "grant_id": "ta3-real-010-0-3c4789c108",
      "source_seed_id": "nf-seed-2026-t3-010",
      "opportunity_number": "T3-010-3c4789c108",
      "opportunity_title": "NATIVE PERFORMING ARTS PROGRAM",
      "agency": "First Peoples Fund",
      "eligibility_text": "NATIVE PERFORMING ARTS PROGRAM",
      "synopsis": "NATIVE PERFORMING ARTS PROGRAM",
      "tribal_eligible": true,
      "applicant_types_include_tribal": true,
      "application_deadline": null,
      "real_fetch": true,
      "fetch_mode": "live",
      "fixture": false,
      "never_synthesized": true,
      "source_url": "https://www.firstpeoplesfund.org/programs/native-performing-arts-program",
      "tier": 3,
      "requires_operator_review": true,
      "ingested_at": "2026-06-30T19:34:18.436126+00:00",
      "provenance": {
        "batch_block": "ta_tier3_foundation",
        "source_seed_id": "nf-seed-2026-t3-010",
        "platform_adapter_key": "foundation_html_listing",
        "adapter_key": "foundation_org_page"
      }
    },
    {
      "grant_id": "ta3-real-011-1-1672e0ccf9",
      "source_seed_id": "nf-seed-2026-t3-011",
      "opportunity_number": "T3-011-1672e0ccf9",
      "opportunity_title": "Investing in the Indigenous Arts Ecology Investing in the Indigenous Arts Ecology examines the impact and evolution of First Peoples Fund\u2019s work over 25 years to develop greater access to the resources Native artists need to succeed. It pro",
      "agency": "First Peoples Fund",
      "eligibility_text": "Investing in the Indigenous Arts Ecology Investing in the Indigenous Arts Ecology examines the impact and evolution of First Peoples Fund\u2019s work over 25 years to develop greater access to the resources Native artists need to succeed. It provides insight into how to best contribute to growing and thriving arts ecosystems in Native communities. EXPLORE THE RESEARCH &gt;&gt;",
      "synopsis": "Investing in the Indigenous Arts Ecology Investing in the Indigenous Arts Ecology examines the impact and evolution of First Peoples Fund\u2019s work over 25 years to develop greater access to the resources Native artists need to succeed. It provides insight into how to best contribute to growing and thriving arts ecosystems in Native communities. EXPLORE THE RESEARCH &gt;&gt;",
      "tribal_eligible": true,
      "applicant_types_include_tribal": true,
      "application_deadline": null,
      "real_fetch": true,
      "fetch_mode": "live",
      "fixture": false,
      "never_synthesized": true,
      "source_url": "http://www.firstpeoplesfund.org/research/investing-in-the-indigenous-arts-ecology",
      "tier": 3,
      "requires_operator_review": true,
      "ingested_at": "2026-06-30T19:34:18.438641+00:00",
      "provenance": {
        "batch_block": "ta_tier3_foundation",
        "source_seed_id": "nf-seed-2026-t3-011",
        "platform_adapter_key": "foundation_html_listing",
        "adapter_key": "foundation_org_page"
      }
    },
    {
      "grant_id": "ta3-real-011-1-1a8e60d288",
      "source_seed_id": "nf-seed-2026-t3-011",
      "opportunity_number": "T3-011-1a8e60d288",
      "opportunity_title": "NATIVE ARTS ECOLOGY BUILDING GRANT",
      "agency": "First Peoples Fund",
      "eligibility_text": "NATIVE ARTS ECOLOGY BUILDING GRANT",
      "synopsis": "NATIVE ARTS ECOLOGY BUILDING GRANT",
      "tribal_eligible": true,
      "applicant_types_include_tribal": true,
      "application_deadline": null,
      "real_fetch": true,
      "fetch_mode": "live",
      "fixture": false,
      "never_synthesized": true,
      "source_url": "https://www.firstpeoplesfund.org/programs/native-arts-ecology-building-grants",
      "tier": 3,
      "requires_operator_review": true,
      "ingested_at": "2026-06-30T19:34:18.438625+00:00",
      "provenance": {
        "batch_block": "ta_tier3_foundation",
        "source_seed_id": "nf-seed-2026-t3-011",
        "platform_adapter_key": "foundation_html_listing",
        "adapter_key": "foundation_org_page"
      }
    },
    {
      "grant_id": "ta3-real-011-1-3c4789c108",
      "source_seed_id": "nf-seed-2026-t3-011",
      "opportunity_number": "T3-011-3c4789c108",
      "opportunity_title": "NATIVE PERFORMING ARTS PROGRAM",
      "agency": "First Peoples Fund",
      "eligibility_text": "NATIVE PERFORMING ARTS PROGRAM",
      "synopsis": "NATIVE PERFORMING ARTS PROGRAM",
      "tribal_eligible": true,
      "applicant_types_include_tribal": true,
      "application_deadline": null,
      "real_fetch": true,
      "fetch_mode": "live",
      "fixture": false,
      "never_synthesized": true,
      "source_url": "https://www.firstpeoplesfund.org/programs/native-performing-arts-program",
      "tier": 3,
      "requires_operator_review": true,
      "ingested_at": "2026-06-30T19:34:18.438593+00:00",
      "provenance": {
        "batch_block": "ta_tier3_foundation",
        "source_seed_id": "nf-seed-2026-t3-011",
        "platform_adapter_key": "foundation_html_listing",
        "adapter_key": "foundation_org_page"
      }
    },
    {
      "grant_id": "ta3-real-012",
      "source_seed_id": "nf-seed-2026-t3-012",
      "opportunity_number": "T3-012",
      "opportunity_title": "Native Agriculture & Food Systems Initiative (NAFSI)",
      "agency": "First Nations Development Institute",
      "eligibility_text": "",
      "tier": 3,
      "synopsis": "Federal grant program: First Nations Development Institute \u2014 Native Agriculture & Food Systems Initiative (NAFSI). No posted NOFO on Grants.gov at ingest (no_live_nofo).",
      "tribal_eligible": false,
      "applicant_types_include_tribal": null,
      "tribal_set_aside": false,
      "tribal_priority_points": false,
      "eligibility_tags": [],
      "source_ingestion_state": "no_live_nofo",
      "no_live_nofo": true,
      "empty_honestly": true,
      "real_fetch": false,
      "fetch_mode": "no_live_nofo",
      "fixture": false,
      "search_live": true,
      "detail_live": false,
      "grants_gov_opportunity_id": null,
      "eligibility_reingest": true,
      "eligibility_reingest_diagnosis": "no_live_nofo:tier3_empty_or_apply_platform_blindspot",
      "prior_eligibility_was_placeholder": false,
      "reingest_program_proxy": false,
      "source_url": "https://www.firstnations.org/grants",
      "never_synthesized": true,
      "honest_labeling": true,
      "provenance": {
        "batch_block": "ta_tier3_foundation",
        "source_seed_id": "nf-seed-2026-t3-012",
        "platform_adapter_key": "foundation_fluxx_embed",
        "empty_honest": true
      }
    },
    {
      "grant_id": "ta3-real-013-3-5e0cc901a1",
      "source_seed_id": "nf-seed-2026-t3-013",
      "opportunity_number": "T3-013-5e0cc901a1",
      "opportunity_title": "Setting the Table for a Healthy Food System in Indian Country Grants,",
      "agency": "First Nations Development Institute",
      "eligibility_text": "Setting the Table for a Healthy Food System in Indian Country Grants,",
      "synopsis": "Setting the Table for a Healthy Food System in Indian Country Grants,",
      "tribal_eligible": true,
      "applicant_types_include_tribal": true,
      "application_deadline": null,
      "real_fetch": true,
      "fetch_mode": "live",
      "fixture": false,
      "never_synthesized": true,
      "source_url": "https://www.firstnations.org/projects/setting-the-table-for-a-healthy-food-system-in-indian-country-grant/",
      "tier": 3,
      "requires_operator_review": true,
      "ingested_at": "2026-06-30T19:34:18.442473+00:00",
      "provenance": {
        "batch_block": "ta_tier3_foundation",
        "source_seed_id": "nf-seed-2026-t3-013",
        "platform_adapter_key": "foundation_fluxx_embed",
        "adapter_key": "foundation_org_page"
      }
    },
    {
      "grant_id": "ta3-real-014-4-b25b20a07f",
      "source_seed_id": "nf-seed-2026-t3-014",
      "opportunity_number": "T3-014-b25b20a07f",
      "opportunity_title": "Scholarships",
      "agency": "American Indian College Fund (AICF)",
      "eligibility_text": "",
      "eligibility_text_source": null,
      "eligibility_provenance": null,
      "grants_gov_doc_type": null,
      "grants_gov_attachment_inventory": null,
      "synopsis": "Scholarships",
      "tribal_eligible": null,
      "applicant_type_ids": [],
      "applicant_types_json": [],
      "applicant_types_include_tribal": null,
      "application_deadline": null,
      "real_fetch": true,
      "fetch_mode": "live",
      "fixture": false,
      "never_synthesized": true,
      "source_url": "https://collegefund.org/students/scholarships",
      "tier": 3,
      "requires_operator_review": true,
      "ingested_at": "2026-07-01T02:20:35.422808+00:00",
      "provenance": {
        "batch_block": "ta_tier3_foundation",
        "source_seed_id": "nf-seed-2026-t3-014",
        "platform_adapter_key": "foundation_html_listing",
        "adapter_key": "foundation_org_page"
      }
    },
    {
      "grant_id": "ta3-real-015-5-18a70777d8",
      "source_seed_id": "nf-seed-2026-t3-015",
      "opportunity_number": "T3-015-18a70777d8",
      "opportunity_title": "Student at a Tribal College/University",
      "agency": "American Indian College Fund (AICF)",
      "eligibility_text": "Student at a Tribal College/University",
      "eligibility_text_source": null,
      "eligibility_provenance": null,
      "grants_gov_doc_type": null,
      "grants_gov_attachment_inventory": null,
      "synopsis": "Student at a Tribal College/University",
      "tribal_eligible": true,
      "applicant_type_ids": [],
      "applicant_types_json": [],
      "applicant_types_include_tribal": true,
      "application_deadline": null,
      "real_fetch": true,
      "fetch_mode": "live",
      "fixture": false,
      "never_synthesized": true,
      "source_url": "https://collegefund.org/students/scholarships/tcu-student/",
      "tier": 3,
      "requires_operator_review": true,
      "ingested_at": "2026-07-01T02:20:35.424908+00:00",
      "provenance": {
        "batch_block": "ta_tier3_foundation",
        "source_seed_id": "nf-seed-2026-t3-015",
        "platform_adapter_key": "foundation_html_listing",
        "adapter_key": "foundation_org_page"
      }
    },
    {
      "grant_id": "ta3-real-015-5-39fe1a176b",
      "source_seed_id": "nf-seed-2026-t3-015",
      "opportunity_number": "T3-015-39fe1a176b",
      "opportunity_title": "Tribal College Transfer Success",
      "agency": "American Indian College Fund (AICF)",
      "eligibility_text": "Tribal College Transfer Success",
      "eligibility_text_source": null,
      "eligibility_provenance": null,
      "grants_gov_doc_type": null,
      "grants_gov_attachment_inventory": null,
      "synopsis": "Tribal College Transfer Success",
      "tribal_eligible": true,
      "applicant_type_ids": [],
      "applicant_types_json": [],
      "applicant_types_include_tribal": true,
      "application_deadline": null,
      "real_fetch": true,
      "fetch_mode": "live",
      "fixture": false,
      "never_synthesized": true,
      "source_url": "https://collegefund.org/students/tribal-college-transfer-success/",
      "tier": 3,
      "requires_operator_review": true,
      "ingested_at": "2026-07-01T02:20:35.424890+00:00",
      "provenance": {
        "batch_block": "ta_tier3_foundation",
        "source_seed_id": "nf-seed-2026-t3-015",
        "platform_adapter_key": "foundation_html_listing",
        "adapter_key": "foundation_org_page"
      }
    },
    {
      "grant_id": "ta3-real-015-5-763467e004",
      "source_seed_id": "nf-seed-2026-t3-015",
      "opportunity_number": "T3-015-763467e004",
      "opportunity_title": "College Access and Success",
      "agency": "American Indian College Fund (AICF)",
      "eligibility_text": "",
      "eligibility_text_source": null,
      "eligibility_provenance": null,
      "grants_gov_doc_type": null,
      "grants_gov_attachment_inventory": null,
      "synopsis": "College Access and Success",
      "tribal_eligible": null,
      "applicant_type_ids": [],
      "applicant_types_json": [],
      "applicant_types_include_tribal": null,
      "application_deadline": null,
      "real_fetch": true,
      "fetch_mode": "live",
      "fixture": false,
      "never_synthesized": true,
      "source_url": "https://collegefund.org/students/college-success/",
      "tier": 3,
      "requires_operator_review": true,
      "ingested_at": "2026-07-01T02:20:35.424857+00:00",
      "provenance": {
        "batch_block": "ta_tier3_foundation",
        "source_seed_id": "nf-seed-2026-t3-015",
        "platform_adapter_key": "foundation_html_listing",
        "adapter_key": "foundation_org_page"
      }
    },
    {
      "grant_id": "ta3-real-015-5-d1db17c960",
      "source_seed_id": "nf-seed-2026-t3-015",
      "opportunity_number": "T3-015-d1db17c960",
      "opportunity_title": "35 accredited Tribal Colleges and Universities (TCU)",
      "agency": "American Indian College Fund (AICF)",
      "eligibility_text": "35 accredited Tribal Colleges and Universities (TCU)",
      "eligibility_text_source": null,
      "eligibility_provenance": null,
      "grants_gov_doc_type": null,
      "grants_gov_attachment_inventory": null,
      "synopsis": "35 accredited Tribal Colleges and Universities (TCU)",
      "tribal_eligible": true,
      "applicant_type_ids": [],
      "applicant_types_json": [],
      "applicant_types_include_tribal": true,
      "application_deadline": null,
      "real_fetch": true,
      "fetch_mode": "live",
      "fixture": false,
      "never_synthesized": true,
      "source_url": "https://collegefund.org/students/tribal-colleges/",
      "tier": 3,
      "requires_operator_review": true,
      "ingested_at": "2026-07-01T02:20:35.424934+00:00",
      "provenance": {
        "batch_block": "ta_tier3_foundation",
        "source_seed_id": "nf-seed-2026-t3-015",
        "platform_adapter_key": "foundation_html_listing",
        "adapter_key": "foundation_org_page"
      }
    },
    {
      "grant_id": "ta3-real-015-5-ecbdd6d729",
      "source_seed_id": "nf-seed-2026-t3-015",
      "opportunity_number": "T3-015-ecbdd6d729",
      "opportunity_title": "Student at a non-Tribal College/University",
      "agency": "American Indian College Fund (AICF)",
      "eligibility_text": "Student at a non-Tribal College/University",
      "eligibility_text_source": null,
      "eligibility_provenance": null,
      "grants_gov_doc_type": null,
      "grants_gov_attachment_inventory": null,
      "synopsis": "Student at a non-Tribal College/University",
      "tribal_eligible": true,
      "applicant_type_ids": [],
      "applicant_types_json": [],
      "applicant_types_include_tribal": true,
      "application_deadline": null,
      "real_fetch": true,
      "fetch_mode": "live",
      "fixture": false,
      "never_synthesized": true,
      "source_url": "https://collegefund.org/students/scholarships/college-students/",
      "tier": 3,
      "requires_operator_review": true,
      "ingested_at": "2026-07-01T02:20:35.424921+00:00",
      "provenance": {
        "batch_block": "ta_tier3_foundation",
        "source_seed_id": "nf-seed-2026-t3-015",
        "platform_adapter_key": "foundation_html_listing",
        "adapter_key": "foundation_org_page"
      }
    },
    {
      "grant_id": "ta3-real-018-8-952ea1f982",
      "source_seed_id": "nf-seed-2026-t3-018",
      "opportunity_number": "T3-018-952ea1f982",
      "opportunity_title": "Scholarship FAQ's",
      "agency": "Association on American Indian Affairs (AAIA)",
      "eligibility_text": "",
      "eligibility_text_source": null,
      "eligibility_provenance": null,
      "grants_gov_doc_type": null,
      "grants_gov_attachment_inventory": null,
      "synopsis": "Scholarship FAQ's",
      "tribal_eligible": null,
      "applicant_type_ids": [],
      "applicant_types_json": [],
      "applicant_types_include_tribal": null,
      "application_deadline": null,
      "real_fetch": true,
      "fetch_mode": "live",
      "fixture": false,
      "never_synthesized": true,
      "source_url": "https://www.indian-affairs.org/scholarshipfaq.html",
      "tier": 3,
      "requires_operator_review": true,
      "ingested_at": "2026-07-01T02:20:35.426845+00:00",
      "provenance": {
        "batch_block": "ta_tier3_foundation",
        "source_seed_id": "nf-seed-2026-t3-018",
        "platform_adapter_key": "foundation_html_listing",
        "adapter_key": "foundation_org_page"
      }
    },
    {
      "grant_id": "ta3-real-019",
      "source_seed_id": "nf-seed-2026-t3-019",
      "opportunity_number": "T3-019",
      "opportunity_title": "Emergency Assistance Fund",
      "agency": "Association on American Indian Affairs (AAIA)",
      "eligibility_text": "",
      "tier": 3,
      "synopsis": "Federal grant program: Association on American Indian Affairs (AAIA) \u2014 Emergency Assistance Fund. No posted NOFO on Grants.gov at ingest (no_live_nofo).",
      "tribal_eligible": false,
      "applicant_types_include_tribal": null,
      "tribal_set_aside": false,
      "tribal_priority_points": false,
      "eligibility_tags": [],
      "source_ingestion_state": "no_live_nofo",
      "no_live_nofo": true,
      "empty_honestly": true,
      "real_fetch": false,
      "fetch_mode": "no_live_nofo",
      "fixture": false,
      "search_live": true,
      "detail_live": false,
      "grants_gov_opportunity_id": null,
      "eligibility_reingest": true,
      "eligibility_reingest_diagnosis": "no_live_nofo:tier3_empty_or_apply_platform_blindspot",
      "prior_eligibility_was_placeholder": false,
      "reingest_program_proxy": false,
      "source_url": "https://www.indian-affairs.org",
      "never_synthesized": true,
      "honest_labeling": true,
      "provenance": {
        "batch_block": "ta_tier3_foundation",
        "source_seed_id": "nf-seed-2026-t3-019",
        "platform_adapter_key": "foundation_html_listing",
        "empty_honest": true
      }
    },
    {
      "grant_id": "ta3-real-020-0-16b4990f82",
      "source_seed_id": "nf-seed-2026-t3-020",
      "opportunity_number": "T3-020-16b4990f82",
      "opportunity_title": "Native CDFI Practitioner Program",
      "agency": "Oweesta Corporation (First Nations Oweesta)",
      "eligibility_text": "Native CDFI Practitioner Program",
      "eligibility_text_source": null,
      "eligibility_provenance": null,
      "grants_gov_doc_type": null,
      "grants_gov_attachment_inventory": null,
      "synopsis": "Native CDFI Practitioner Program",
      "tribal_eligible": true,
      "applicant_type_ids": [],
      "applicant_types_json": [],
      "applicant_types_include_tribal": true,
      "application_deadline": null,
      "real_fetch": true,
      "fetch_mode": "live",
      "fixture": false,
      "never_synthesized": true,
      "source_url": "https://www.oweesta.org/native-cdfi-practitioner-program/",
      "tier": 3,
      "requires_operator_review": true,
      "ingested_at": "2026-07-01T02:20:35.417882+00:00",
      "provenance": {
        "batch_block": "ta_tier3_foundation",
        "source_seed_id": "nf-seed-2026-t3-020",
        "platform_adapter_key": "foundation_html_listing",
        "adapter_key": "foundation_org_page"
      }
    },
    {
      "grant_id": "ta3-real-021-1-16b4990f82",
      "source_seed_id": "nf-seed-2026-t3-021",
      "opportunity_number": "T3-021-16b4990f82",
      "opportunity_title": "Native CDFI Practitioner Program",
      "agency": "Oweesta Corporation (First Nations Oweesta)",
      "eligibility_text": "Native CDFI Practitioner Program",
      "eligibility_text_source": null,
      "eligibility_provenance": null,
      "grants_gov_doc_type": null,
      "grants_gov_attachment_inventory": null,
      "synopsis": "Native CDFI Practitioner Program",
      "tribal_eligible": true,
      "applicant_type_ids": [],
      "applicant_types_json": [],
      "applicant_types_include_tribal": true,
      "application_deadline": null,
      "real_fetch": true,
      "fetch_mode": "live",
      "fixture": false,
      "never_synthesized": true,
      "source_url": "https://www.oweesta.org/native-cdfi-practitioner-program/",
      "tier": 3,
      "requires_operator_review": true,
      "ingested_at": "2026-07-01T02:20:35.419513+00:00",
      "provenance": {
        "batch_block": "ta_tier3_foundation",
        "source_seed_id": "nf-seed-2026-t3-021",
        "platform_adapter_key": "foundation_html_listing",
        "adapter_key": "foundation_org_page"
      }
    },
    {
      "grant_id": "ta3-real-022-2-2b9877b68b",
      "source_seed_id": "nf-seed-2026-t3-022",
      "opportunity_number": "T3-022-2b9877b68b",
      "opportunity_title": "Navajo Relief Fund\u00ae (NRF)",
      "agency": "Partnership with Native Americans (PWNA)",
      "eligibility_text": "",
      "eligibility_text_source": null,
      "eligibility_provenance": null,
      "grants_gov_doc_type": null,
      "grants_gov_attachment_inventory": null,
      "synopsis": "Navajo Relief Fund\u00ae (NRF)",
      "tribal_eligible": null,
      "applicant_type_ids": [],
      "applicant_types_json": [],
      "applicant_types_include_tribal": null,
      "application_deadline": null,
      "real_fetch": true,
      "fetch_mode": "live",
      "fixture": false,
      "never_synthesized": true,
      "source_url": "https://nativepartnership.org/nrf/",
      "tier": 3,
      "requires_operator_review": true,
      "ingested_at": "2026-07-01T02:20:35.430228+00:00",
      "provenance": {
        "batch_block": "ta_tier3_foundation",
        "source_seed_id": "nf-seed-2026-t3-022",
        "platform_adapter_key": "foundation_html_listing",
        "adapter_key": "foundation_org_page"
      }
    },
    {
      "grant_id": "ta3-real-022-2-75f231431f",
      "source_seed_id": "nf-seed-2026-t3-022",
      "opportunity_number": "T3-022-75f231431f",
      "opportunity_title": "5 Funding Facts",
      "agency": "Partnership with Native Americans (PWNA)",
      "eligibility_text": "",
      "eligibility_text_source": null,
      "eligibility_provenance": null,
      "grants_gov_doc_type": null,
      "grants_gov_attachment_inventory": null,
      "synopsis": "5 Funding Facts",
      "tribal_eligible": null,
      "applicant_type_ids": [],
      "applicant_types_json": [],
      "applicant_types_include_tribal": null,
      "application_deadline": null,
      "real_fetch": true,
      "fetch_mode": "live",
      "fixture": false,
      "never_synthesized": true,
      "source_url": "https://nativepartnership.org/5-funding-facts/",
      "tier": 3,
      "requires_operator_review": true,
      "ingested_at": "2026-07-01T02:20:35.430273+00:00",
      "provenance": {
        "batch_block": "ta_tier3_foundation",
        "source_seed_id": "nf-seed-2026-t3-022",
        "platform_adapter_key": "foundation_html_listing",
        "adapter_key": "foundation_org_page"
      }
    },
    {
      "grant_id": "ta3-real-022-2-8deb5e0328",
      "source_seed_id": "nf-seed-2026-t3-022",
      "opportunity_number": "T3-022-8deb5e0328",
      "opportunity_title": "Emergency Services",
      "agency": "Partnership with Native Americans (PWNA)",
      "eligibility_text": "",
      "eligibility_text_source": null,
      "eligibility_provenance": null,
      "grants_gov_doc_type": null,
      "grants_gov_attachment_inventory": null,
      "synopsis": "Emergency Services",
      "tribal_eligible": null,
      "applicant_type_ids": [],
      "applicant_types_json": [],
      "applicant_types_include_tribal": null,
      "application_deadline": null,
      "real_fetch": true,
      "fetch_mode": "live",
      "fixture": false,
      "never_synthesized": true,
      "source_url": "https://nativepartnership.org/emergency-services/",
      "tier": 3,
      "requires_operator_review": true,
      "ingested_at": "2026-07-01T02:20:35.430260+00:00",
      "provenance": {
        "batch_block": "ta_tier3_foundation",
        "source_seed_id": "nf-seed-2026-t3-022",
        "platform_adapter_key": "foundation_html_listing",
        "adapter_key": "foundation_org_page"
      }
    },
    {
      "grant_id": "ta3-real-022-2-d26c9b8f62",
      "source_seed_id": "nf-seed-2026-t3-022",
      "opportunity_number": "T3-022-d26c9b8f62",
      "opportunity_title": "American Indian Education Fund\u00ae (AIEF)",
      "agency": "Partnership with Native Americans (PWNA)",
      "eligibility_text": "American Indian Education Fund\u00ae (AIEF)",
      "eligibility_text_source": null,
      "eligibility_provenance": null,
      "grants_gov_doc_type": null,
      "grants_gov_attachment_inventory": null,
      "synopsis": "American Indian Education Fund\u00ae (AIEF)",
      "tribal_eligible": true,
      "applicant_type_ids": [],
      "applicant_types_json": [],
      "applicant_types_include_tribal": true,
      "application_deadline": null,
      "real_fetch": true,
      "fetch_mode": "live",
      "fixture": false,
      "never_synthesized": true,
      "source_url": "https://nativepartnership.org/aief/",
      "tier": 3,
      "requires_operator_review": true,
      "ingested_at": "2026-07-01T02:20:35.430202+00:00",
      "provenance": {
        "batch_block": "ta_tier3_foundation",
        "source_seed_id": "nf-seed-2026-t3-022",
        "platform_adapter_key": "foundation_html_listing",
        "adapter_key": "foundation_org_page"
      }
    },
    {
      "grant_id": "ta3-real-022-2-e22d3fdff1",
      "source_seed_id": "nf-seed-2026-t3-022",
      "opportunity_number": "T3-022-e22d3fdff1",
      "opportunity_title": "Sioux Nation Relief Fund\u00ae (SNRF)",
      "agency": "Partnership with Native Americans (PWNA)",
      "eligibility_text": "",
      "eligibility_text_source": null,
      "eligibility_provenance": null,
      "grants_gov_doc_type": null,
      "grants_gov_attachment_inventory": null,
      "synopsis": "Sioux Nation Relief Fund\u00ae (SNRF)",
      "tribal_eligible": null,
      "applicant_type_ids": [],
      "applicant_types_json": [],
      "applicant_types_include_tribal": null,
      "application_deadline": null,
      "real_fetch": true,
      "fetch_mode": "live",
      "fixture": false,
      "never_synthesized": true,
      "source_url": "https://nativepartnership.org/snrf/",
      "tier": 3,
      "requires_operator_review": true,
      "ingested_at": "2026-07-01T02:20:35.430247+00:00",
      "provenance": {
        "batch_block": "ta_tier3_foundation",
        "source_seed_id": "nf-seed-2026-t3-022",
        "platform_adapter_key": "foundation_html_listing",
        "adapter_key": "foundation_org_page"
      }
    },
    {
      "grant_id": "ta3-real-024",
      "source_seed_id": "nf-seed-2026-t3-024",
      "opportunity_number": "T3-024",
      "opportunity_title": "Community Grants",
      "agency": "Running Strong for American Indian Youth",
      "eligibility_text": "",
      "tier": 3,
      "synopsis": "Federal grant program: Running Strong for American Indian Youth \u2014 Community Grants. No posted NOFO on Grants.gov at ingest (no_live_nofo).",
      "tribal_eligible": false,
      "applicant_types_include_tribal": null,
      "tribal_set_aside": false,
      "tribal_priority_points": false,
      "eligibility_tags": [],
      "source_ingestion_state": "no_live_nofo",
      "no_live_nofo": true,
      "empty_honestly": true,
      "real_fetch": false,
      "fetch_mode": "no_live_nofo",
      "fixture": false,
      "search_live": true,
      "detail_live": false,
      "grants_gov_opportunity_id": null,
      "eligibility_reingest": true,
      "eligibility_reingest_diagnosis": "no_live_nofo:tier3_empty_or_apply_platform_blindspot",
      "prior_eligibility_was_placeholder": false,
      "reingest_program_proxy": false,
      "source_url": "https://indianyouth.org",
      "never_synthesized": true,
      "honest_labeling": true,
      "provenance": {
        "batch_block": "ta_tier3_foundation",
        "source_seed_id": "nf-seed-2026-t3-024",
        "platform_adapter_key": "foundation_html_listing",
        "empty_honest": true
      }
    },
    {
      "grant_id": "ta3-real-025-5-4027c575d9",
      "source_seed_id": "nf-seed-2026-t3-025",
      "opportunity_number": "T3-025-4027c575d9",
      "opportunity_title": "Economic Advancement Grants for Local Empowerment (EAGLE)",
      "agency": "ANA Pacific / Native Hawaiian Organizations",
      "eligibility_text": "",
      "eligibility_text_source": null,
      "eligibility_provenance": null,
      "grants_gov_doc_type": null,
      "grants_gov_attachment_inventory": null,
      "synopsis": "Economic Advancement Grants for Local Empowerment (EAGLE)",
      "tribal_eligible": null,
      "applicant_type_ids": [],
      "applicant_types_json": [],
      "applicant_types_include_tribal": null,
      "application_deadline": null,
      "real_fetch": true,
      "fetch_mode": "live",
      "fixture": false,
      "never_synthesized": true,
      "source_url": "https://www.anapacific.org/grants/economic-advancement-grants-local-empowerment/",
      "tier": 3,
      "requires_operator_review": true,
      "ingested_at": "2026-07-01T02:53:41.250608+00:00",
      "provenance": {
        "batch_block": "ta_tier3_foundation",
        "source_seed_id": "nf-seed-2026-t3-025",
        "platform_adapter_key": "foundation_html_listing",
        "adapter_key": "foundation_org_page"
      }
    },
    {
      "grant_id": "ta3-real-026-6-d6366e67ae",
      "source_seed_id": "nf-seed-2026-t3-026",
      "opportunity_number": "T3-026-d6366e67ae",
      "opportunity_title": "Scholarship Policies",
      "agency": "AISES (American Indian Science & Engineering Society)",
      "eligibility_text": "",
      "eligibility_text_source": null,
      "eligibility_provenance": null,
      "grants_gov_doc_type": null,
      "grants_gov_attachment_inventory": null,
      "synopsis": "Scholarship Policies",
      "tribal_eligible": null,
      "applicant_type_ids": [],
      "applicant_types_json": [],
      "applicant_types_include_tribal": null,
      "application_deadline": null,
      "real_fetch": true,
      "fetch_mode": "live",
      "fixture": false,
      "never_synthesized": true,
      "source_url": "https://aises.org/scholarship-internship-oasis-policies/",
      "tier": 3,
      "requires_operator_review": true,
      "ingested_at": "2026-07-01T02:20:35.440419+00:00",
      "provenance": {
        "batch_block": "ta_tier3_foundation",
        "source_seed_id": "nf-seed-2026-t3-026",
        "platform_adapter_key": "foundation_html_listing",
        "adapter_key": "foundation_org_page"
      }
    },
    {
      "grant_id": "ta3-real-026-6-f0ef126b7b",
      "source_seed_id": "nf-seed-2026-t3-026",
      "opportunity_number": "T3-026-f0ef126b7b",
      "opportunity_title": "Scholarship Application Walk Through",
      "agency": "AISES (American Indian Science & Engineering Society)",
      "eligibility_text": "",
      "eligibility_text_source": null,
      "eligibility_provenance": null,
      "grants_gov_doc_type": null,
      "grants_gov_attachment_inventory": null,
      "synopsis": "Scholarship Application Walk Through",
      "tribal_eligible": null,
      "applicant_type_ids": [],
      "applicant_types_json": [],
      "applicant_types_include_tribal": null,
      "application_deadline": null,
      "real_fetch": true,
      "fetch_mode": "live",
      "fixture": false,
      "never_synthesized": true,
      "source_url": "https://youtu.be/hv89w6OaY2A",
      "tier": 3,
      "requires_operator_review": true,
      "ingested_at": "2026-07-01T02:20:35.440361+00:00",
      "provenance": {
        "batch_block": "ta_tier3_foundation",
        "source_seed_id": "nf-seed-2026-t3-026",
        "platform_adapter_key": "foundation_html_listing",
        "adapter_key": "foundation_org_page"
      }
    },
    {
      "grant_id": "ta3-real-027",
      "source_seed_id": "nf-seed-2026-t3-027",
      "opportunity_number": "T3-027",
      "opportunity_title": "Environmental Justice Grants",
      "agency": "Honor the Earth",
      "eligibility_text": "",
      "tier": 3,
      "synopsis": "Federal grant program: Honor the Earth \u2014 Environmental Justice Grants. No posted NOFO on Grants.gov at ingest (no_live_nofo).",
      "tribal_eligible": false,
      "applicant_types_include_tribal": null,
      "tribal_set_aside": false,
      "tribal_priority_points": false,
      "eligibility_tags": [],
      "source_ingestion_state": "no_live_nofo",
      "no_live_nofo": true,
      "empty_honestly": true,
      "real_fetch": false,
      "fetch_mode": "no_live_nofo",
      "fixture": false,
      "search_live": true,
      "detail_live": false,
      "grants_gov_opportunity_id": null,
      "eligibility_reingest": true,
      "eligibility_reingest_diagnosis": "no_live_nofo:tier3_empty_or_apply_platform_blindspot",
      "prior_eligibility_was_placeholder": false,
      "reingest_program_proxy": false,
      "source_url": "https://www.honorearth.org",
      "never_synthesized": true,
      "honest_labeling": true,
      "provenance": {
        "batch_block": "ta_tier3_foundation",
        "source_seed_id": "nf-seed-2026-t3-027",
        "platform_adapter_key": "foundation_html_listing",
        "empty_honest": true
      }
    },
    {
      "grant_id": "ta3-real-030",
      "source_seed_id": "nf-seed-2026-t3-030",
      "opportunity_number": "T3-030",
      "opportunity_title": "Project Grants",
      "agency": "Seventh Generation Fund for Indigenous Peoples",
      "eligibility_text": "",
      "tier": 3,
      "synopsis": "Federal grant program: Seventh Generation Fund for Indigenous Peoples \u2014 Project Grants. No posted NOFO on Grants.gov at ingest (no_live_nofo).",
      "tribal_eligible": false,
      "applicant_types_include_tribal": null,
      "tribal_set_aside": false,
      "tribal_priority_points": false,
      "eligibility_tags": [],
      "source_ingestion_state": "no_live_nofo",
      "no_live_nofo": true,
      "empty_honestly": true,
      "real_fetch": false,
      "fetch_mode": "no_live_nofo",
      "fixture": false,
      "search_live": true,
      "detail_live": false,
      "grants_gov_opportunity_id": null,
      "eligibility_reingest": true,
      "eligibility_reingest_diagnosis": "no_live_nofo:tier3_empty_or_apply_platform_blindspot",
      "prior_eligibility_was_placeholder": false,
      "reingest_program_proxy": false,
      "source_url": "https://7genfund.org",
      "never_synthesized": true,
      "honest_labeling": true,
      "provenance": {
        "batch_block": "ta_tier3_foundation",
        "source_seed_id": "nf-seed-2026-t3-030",
        "platform_adapter_key": "foundation_html_listing",
        "empty_honest": true
      }
    },
    {
      "grant_id": "ta3-real-034",
      "source_seed_id": "nf-seed-2026-t3-034",
      "opportunity_number": "T3-034",
      "opportunity_title": "Investing in Native Community Assets",
      "agency": "First Nations Development Institute",
      "eligibility_text": "",
      "tier": 3,
      "synopsis": "Federal grant program: First Nations Development Institute \u2014 Investing in Native Community Assets. No posted NOFO on Grants.gov at ingest (no_live_nofo).",
      "tribal_eligible": false,
      "applicant_types_include_tribal": null,
      "tribal_set_aside": false,
      "tribal_priority_points": false,
      "eligibility_tags": [],
      "source_ingestion_state": "no_live_nofo",
      "no_live_nofo": true,
      "empty_honestly": true,
      "real_fetch": false,
      "fetch_mode": "no_live_nofo",
      "fixture": false,
      "search_live": true,
      "detail_live": false,
      "grants_gov_opportunity_id": null,
      "eligibility_reingest": true,
      "eligibility_reingest_diagnosis": "no_live_nofo:tier3_empty_or_apply_platform_blindspot",
      "prior_eligibility_was_placeholder": false,
      "reingest_program_proxy": false,
      "source_url": "https://www.firstnations.org/grants",
      "never_synthesized": true,
      "honest_labeling": true,
      "provenance": {
        "batch_block": "ta_tier3_foundation",
        "source_seed_id": "nf-seed-2026-t3-034",
        "platform_adapter_key": "foundation_fluxx_embed",
        "empty_honest": true
      }
    },
    {
      "grant_id": "ta3-real-035",
      "source_seed_id": "nf-seed-2026-t3-035",
      "opportunity_number": "T3-035",
      "opportunity_title": "Truth, Racial Healing & Transformation \u2013 Native track",
      "agency": "W.K. Kellogg Foundation",
      "eligibility_text": "",
      "tier": 3,
      "synopsis": "Federal grant program: W.K. Kellogg Foundation \u2014 Truth, Racial Healing & Transformation \u2013 Native track. No posted NOFO on Grants.gov at ingest (no_live_nofo).",
      "tribal_eligible": false,
      "applicant_types_include_tribal": null,
      "tribal_set_aside": false,
      "tribal_priority_points": false,
      "eligibility_tags": [],
      "source_ingestion_state": "no_live_nofo",
      "no_live_nofo": true,
      "empty_honestly": true,
      "real_fetch": false,
      "fetch_mode": "no_live_nofo",
      "fixture": false,
      "search_live": true,
      "detail_live": false,
      "grants_gov_opportunity_id": null,
      "eligibility_reingest": true,
      "eligibility_reingest_diagnosis": "no_live_nofo:tier3_empty_or_apply_platform_blindspot",
      "prior_eligibility_was_placeholder": false,
      "reingest_program_proxy": false,
      "source_url": "https://www.wkkf.org/what-we-do/racial-equity/truth-racial-healing-transformation",
      "never_synthesized": true,
      "honest_labeling": true,
      "provenance": {
        "batch_block": "ta_tier3_foundation",
        "source_seed_id": "nf-seed-2026-t3-035",
        "platform_adapter_key": "foundation_html_listing",
        "empty_honest": true
      }
    },
    {
      "grant_id": "ta3-real-036",
      "source_seed_id": "nf-seed-2026-t3-036",
      "opportunity_number": "T3-036",
      "opportunity_title": "Community Health Grants",
      "agency": "Native Health Initiative (NHI)",
      "eligibility_text": "",
      "tier": 3,
      "synopsis": "Federal grant program: Native Health Initiative (NHI) \u2014 Community Health Grants. No posted NOFO on Grants.gov at ingest (no_live_nofo).",
      "tribal_eligible": false,
      "applicant_types_include_tribal": null,
      "tribal_set_aside": false,
      "tribal_priority_points": false,
      "eligibility_tags": [],
      "source_ingestion_state": "no_live_nofo",
      "no_live_nofo": true,
      "empty_honestly": true,
      "real_fetch": false,
      "fetch_mode": "no_live_nofo",
      "fixture": false,
      "search_live": true,
      "detail_live": false,
      "grants_gov_opportunity_id": null,
      "eligibility_reingest": true,
      "eligibility_reingest_diagnosis": "no_live_nofo:tier3_empty_or_apply_platform_blindspot",
      "prior_eligibility_was_placeholder": false,
      "reingest_program_proxy": false,
      "source_url": "https://nativehealthinitiative.org",
      "never_synthesized": true,
      "honest_labeling": true,
      "provenance": {
        "batch_block": "ta_tier3_foundation",
        "source_seed_id": "nf-seed-2026-t3-036",
        "platform_adapter_key": "foundation_html_listing",
        "empty_honest": true
      }
    },
    {
      "grant_id": "ta3-real-037-7-39f19cf88f",
      "source_seed_id": "nf-seed-2026-t3-037",
      "opportunity_number": "T3-037-39f19cf88f",
      "opportunity_title": "AIHEC AIMS",
      "agency": "Tribal College Fund \u2013 American Indian Higher Education Consortium (AIHEC)",
      "eligibility_text": "",
      "eligibility_text_source": null,
      "eligibility_provenance": null,
      "grants_gov_doc_type": null,
      "grants_gov_attachment_inventory": null,
      "synopsis": "AIHEC AIMS",
      "tribal_eligible": null,
      "applicant_type_ids": [],
      "applicant_types_json": [],
      "applicant_types_include_tribal": null,
      "application_deadline": null,
      "real_fetch": true,
      "fetch_mode": "live",
      "fixture": false,
      "never_synthesized": true,
      "source_url": "https://www.aihec.org/student-success/research/aihec-aims/",
      "tier": 3,
      "requires_operator_review": true,
      "ingested_at": "2026-07-01T02:53:41.246909+00:00",
      "provenance": {
        "batch_block": "ta_tier3_foundation",
        "source_seed_id": "nf-seed-2026-t3-037",
        "platform_adapter_key": "foundation_html_listing",
        "adapter_key": "foundation_org_page"
      }
    },
    {
      "grant_id": "ta3-real-044",
      "source_seed_id": "nf-seed-2026-t3-044",
      "opportunity_number": "T3-044",
      "opportunity_title": "AFN Policy & Capacity Grants",
      "agency": "Alaska Federation of Natives (AFN)",
      "eligibility_text": "",
      "tier": 3,
      "synopsis": "Federal grant program: Alaska Federation of Natives (AFN) \u2014 AFN Policy & Capacity Grants. No posted NOFO on Grants.gov at ingest (no_live_nofo).",
      "tribal_eligible": false,
      "applicant_types_include_tribal": null,
      "tribal_set_aside": false,
      "tribal_priority_points": false,
      "eligibility_tags": [],
      "source_ingestion_state": "no_live_nofo",
      "no_live_nofo": true,
      "empty_honestly": true,
      "real_fetch": false,
      "fetch_mode": "no_live_nofo",
      "fixture": false,
      "search_live": true,
      "detail_live": false,
      "grants_gov_opportunity_id": null,
      "eligibility_reingest": true,
      "eligibility_reingest_diagnosis": "no_live_nofo:tier3_empty_or_apply_platform_blindspot",
      "prior_eligibility_was_placeholder": false,
      "reingest_program_proxy": false,
      "source_url": "https://www.nativefederation.org",
      "never_synthesized": true,
      "honest_labeling": true,
      "provenance": {
        "batch_block": "ta_tier3_foundation",
        "source_seed_id": "nf-seed-2026-t3-044",
        "platform_adapter_key": "foundation_html_listing",
        "empty_honest": true
      }
    },
    {
      "grant_id": "ta3-real-047-7-be00297988",
      "source_seed_id": "nf-seed-2026-t3-047",
      "opportunity_number": "T3-047-be00297988",
      "opportunity_title": "Community Planning &#038; Development",
      "agency": "Kawerak Inc.",
      "eligibility_text": "",
      "eligibility_text_source": null,
      "eligibility_provenance": null,
      "grants_gov_doc_type": null,
      "grants_gov_attachment_inventory": null,
      "synopsis": "Community Planning &#038; Development",
      "tribal_eligible": null,
      "applicant_type_ids": [],
      "applicant_types_json": [],
      "applicant_types_include_tribal": null,
      "application_deadline": null,
      "real_fetch": true,
      "fetch_mode": "live",
      "fixture": false,
      "never_synthesized": true,
      "source_url": "https://kawerak.org/cultural-development/community-planning-and-development/",
      "tier": 3,
      "requires_operator_review": true,
      "ingested_at": "2026-07-01T02:53:41.254359+00:00",
      "provenance": {
        "batch_block": "ta_tier3_foundation",
        "source_seed_id": "nf-seed-2026-t3-047",
        "platform_adapter_key": "foundation_html_listing",
        "adapter_key": "foundation_org_page"
      }
    },
    {
      "grant_id": "ta3-real-053",
      "source_seed_id": "nf-seed-2026-t3-053",
      "opportunity_number": "T3-053",
      "opportunity_title": "NNABA Legal Education Grants",
      "agency": "National Native American Bar Association (NNABA)",
      "eligibility_text": "",
      "tier": 3,
      "synopsis": "Federal grant program: National Native American Bar Association (NNABA) \u2014 NNABA Legal Education Grants. No posted NOFO on Grants.gov at ingest (no_live_nofo).",
      "tribal_eligible": false,
      "applicant_types_include_tribal": null,
      "tribal_set_aside": false,
      "tribal_priority_points": false,
      "eligibility_tags": [],
      "source_ingestion_state": "no_live_nofo",
      "no_live_nofo": true,
      "empty_honestly": true,
      "real_fetch": false,
      "fetch_mode": "no_live_nofo",
      "fixture": false,
      "search_live": true,
      "detail_live": false,
      "grants_gov_opportunity_id": null,
      "eligibility_reingest": true,
      "eligibility_reingest_diagnosis": "no_live_nofo:tier3_empty_or_apply_platform_blindspot",
      "prior_eligibility_was_placeholder": false,
      "reingest_program_proxy": false,
      "source_url": "https://www.nativeamericanbar.org",
      "never_synthesized": true,
      "honest_labeling": true,
      "provenance": {
        "batch_block": "ta_tier3_foundation",
        "source_seed_id": "nf-seed-2026-t3-053",
        "platform_adapter_key": "foundation_html_listing",
        "empty_honest": true
      }
    },
    {
      "grant_id": "ta3-real-054-4-16b4990f82",
      "source_seed_id": "nf-seed-2026-t3-054",
      "opportunity_number": "T3-054-16b4990f82",
      "opportunity_title": "Native CDFI Practitioner Program",
      "agency": "First Nations Oweesta Corporation",
      "eligibility_text": "Native CDFI Practitioner Program",
      "eligibility_text_source": null,
      "eligibility_provenance": null,
      "grants_gov_doc_type": null,
      "grants_gov_attachment_inventory": null,
      "synopsis": "Native CDFI Practitioner Program",
      "tribal_eligible": true,
      "applicant_type_ids": [],
      "applicant_types_json": [],
      "applicant_types_include_tribal": true,
      "application_deadline": null,
      "real_fetch": true,
      "fetch_mode": "live",
      "fixture": false,
      "never_synthesized": true,
      "source_url": "https://www.oweesta.org/native-cdfi-practitioner-program/",
      "tier": 3,
      "requires_operator_review": true,
      "ingested_at": "2026-07-01T02:20:35.421168+00:00",
      "provenance": {
        "batch_block": "ta_tier3_foundation",
        "source_seed_id": "nf-seed-2026-t3-054",
        "platform_adapter_key": "foundation_html_listing",
        "adapter_key": "foundation_org_page"
      }
    },
    {
      "grant_id": "ta3-real-055",
      "source_seed_id": "nf-seed-2026-t3-055",
      "opportunity_number": "T3-055",
      "opportunity_title": "NARF Pro Bono / Litigation Support",
      "agency": "Native American Rights Fund (NARF)",
      "eligibility_text": "",
      "tier": 3,
      "synopsis": "Federal grant program: Native American Rights Fund (NARF) \u2014 NARF Pro Bono / Litigation Support. No posted NOFO on Grants.gov at ingest (no_live_nofo).",
      "tribal_eligible": false,
      "applicant_types_include_tribal": null,
      "tribal_set_aside": false,
      "tribal_priority_points": false,
      "eligibility_tags": [],
      "source_ingestion_state": "no_live_nofo",
      "no_live_nofo": true,
      "empty_honestly": true,
      "real_fetch": false,
      "fetch_mode": "no_live_nofo",
      "fixture": false,
      "search_live": true,
      "detail_live": false,
      "grants_gov_opportunity_id": null,
      "eligibility_reingest": true,
      "eligibility_reingest_diagnosis": "no_live_nofo:tier3_empty_or_apply_platform_blindspot",
      "prior_eligibility_was_placeholder": false,
      "reingest_program_proxy": false,
      "source_url": "https://www.narf.org",
      "never_synthesized": true,
      "honest_labeling": true,
      "provenance": {
        "batch_block": "ta_tier3_foundation",
        "source_seed_id": "nf-seed-2026-t3-055",
        "platform_adapter_key": "foundation_html_listing",
        "empty_honest": true
      }
    },
    {
      "grant_id": "ta3-real-056-6-115bc724e2",
      "source_seed_id": "nf-seed-2026-t3-056",
      "opportunity_number": "T3-056-115bc724e2",
      "opportunity_title": "Community Programs",
      "agency": "Council for Native Hawaiian Advancement (CNHA)",
      "eligibility_text": "",
      "eligibility_text_source": null,
      "eligibility_provenance": null,
      "grants_gov_doc_type": null,
      "grants_gov_attachment_inventory": null,
      "synopsis": "Community Programs",
      "tribal_eligible": null,
      "applicant_type_ids": [],
      "applicant_types_json": [],
      "applicant_types_include_tribal": null,
      "application_deadline": null,
      "real_fetch": true,
      "fetch_mode": "live",
      "fixture": false,
      "never_synthesized": true,
      "source_url": "https://hawaiiancouncil.org/programs/",
      "tier": 3,
      "requires_operator_review": true,
      "ingested_at": "2026-07-01T02:53:41.245210+00:00",
      "provenance": {
        "batch_block": "ta_tier3_foundation",
        "source_seed_id": "nf-seed-2026-t3-056",
        "platform_adapter_key": "foundation_html_listing",
        "adapter_key": "foundation_org_page"
      }
    },
    {
      "grant_id": "ta3-real-056-6-424c50a7d2",
      "source_seed_id": "nf-seed-2026-t3-056",
      "opportunity_number": "T3-056-424c50a7d2",
      "opportunity_title": "Community Programs",
      "agency": "Council for Native Hawaiian Advancement (CNHA)",
      "eligibility_text": "",
      "eligibility_text_source": null,
      "eligibility_provenance": null,
      "grants_gov_doc_type": null,
      "grants_gov_attachment_inventory": null,
      "synopsis": "Community Programs",
      "tribal_eligible": null,
      "applicant_type_ids": [],
      "applicant_types_json": [],
      "applicant_types_include_tribal": null,
      "application_deadline": null,
      "real_fetch": true,
      "fetch_mode": "live",
      "fixture": false,
      "never_synthesized": true,
      "source_url": "https://www.hawaiiancouncil.org/programs/",
      "tier": 3,
      "requires_operator_review": true,
      "ingested_at": "2026-07-01T02:53:41.245179+00:00",
      "provenance": {
        "batch_block": "ta_tier3_foundation",
        "source_seed_id": "nf-seed-2026-t3-056",
        "platform_adapter_key": "foundation_html_listing",
        "adapter_key": "foundation_org_page"
      }
    },
    {
      "grant_id": "ta3-real-059",
      "source_seed_id": "nf-seed-2026-t3-059",
      "opportunity_number": "T3-059",
      "opportunity_title": "Native Hawaiian Education Program (NHEP) Sub-grants",
      "agency": "Native Hawaiian Education Council (NHEC)",
      "eligibility_text": "",
      "tier": 3,
      "synopsis": "Federal grant program: Native Hawaiian Education Council (NHEC) \u2014 Native Hawaiian Education Program (NHEP) Sub-grants. No posted NOFO on Grants.gov at ingest (no_live_nofo).",
      "tribal_eligible": false,
      "applicant_types_include_tribal": null,
      "tribal_set_aside": false,
      "tribal_priority_points": false,
      "eligibility_tags": [],
      "source_ingestion_state": "no_live_nofo",
      "no_live_nofo": true,
      "empty_honestly": true,
      "real_fetch": false,
      "fetch_mode": "no_live_nofo",
      "fixture": false,
      "search_live": true,
      "detail_live": false,
      "grants_gov_opportunity_id": null,
      "eligibility_reingest": true,
      "eligibility_reingest_diagnosis": "no_live_nofo:tier3_empty_or_apply_platform_blindspot",
      "prior_eligibility_was_placeholder": false,
      "reingest_program_proxy": false,
      "source_url": "https://nhec.net",
      "never_synthesized": true,
      "honest_labeling": true,
      "provenance": {
        "batch_block": "ta_tier3_foundation",
        "source_seed_id": "nf-seed-2026-t3-059",
        "platform_adapter_key": "foundation_html_listing",
        "empty_honest": true
      }
    },
    {
      "grant_id": "ta3-real-062",
      "source_seed_id": "nf-seed-2026-t3-062",
      "opportunity_number": "T3-062",
      "opportunity_title": "TOCA Food Sovereignty Grants",
      "agency": "Tohono O'odham Community Action (TOCA)",
      "eligibility_text": "",
      "tier": 3,
      "synopsis": "Federal grant program: Tohono O'odham Community Action (TOCA) \u2014 TOCA Food Sovereignty Grants. No posted NOFO on Grants.gov at ingest (no_live_nofo).",
      "tribal_eligible": false,
      "applicant_types_include_tribal": null,
      "tribal_set_aside": false,
      "tribal_priority_points": false,
      "eligibility_tags": [],
      "source_ingestion_state": "no_live_nofo",
      "no_live_nofo": true,
      "empty_honestly": true,
      "real_fetch": false,
      "fetch_mode": "no_live_nofo",
      "fixture": false,
      "search_live": true,
      "detail_live": false,
      "grants_gov_opportunity_id": null,
      "eligibility_reingest": true,
      "eligibility_reingest_diagnosis": "no_live_nofo:tier3_empty_or_apply_platform_blindspot",
      "prior_eligibility_was_placeholder": false,
      "reingest_program_proxy": false,
      "source_url": "https://www.tocaonline.org",
      "never_synthesized": true,
      "honest_labeling": true,
      "provenance": {
        "batch_block": "ta_tier3_foundation",
        "source_seed_id": "nf-seed-2026-t3-062",
        "platform_adapter_key": "foundation_html_listing",
        "empty_honest": true
      }
    },
    {
      "grant_id": "ta3-real-063",
      "source_seed_id": "nf-seed-2026-t3-063",
      "opportunity_number": "T3-063",
      "opportunity_title": "IAC Tribal Agriculture Technical Assistance Grants",
      "agency": "Intertribal Agriculture Council (IAC)",
      "eligibility_text": "",
      "tier": 3,
      "synopsis": "Federal grant program: Intertribal Agriculture Council (IAC) \u2014 IAC Tribal Agriculture Technical Assistance Grants. No posted NOFO on Grants.gov at ingest (no_live_nofo).",
      "tribal_eligible": false,
      "applicant_types_include_tribal": null,
      "tribal_set_aside": false,
      "tribal_priority_points": false,
      "eligibility_tags": [],
      "source_ingestion_state": "no_live_nofo",
      "no_live_nofo": true,
      "empty_honestly": true,
      "real_fetch": false,
      "fetch_mode": "no_live_nofo",
      "fixture": false,
      "search_live": true,
      "detail_live": false,
      "grants_gov_opportunity_id": null,
      "eligibility_reingest": true,
      "eligibility_reingest_diagnosis": "no_live_nofo:tier3_empty_or_apply_platform_blindspot",
      "prior_eligibility_was_placeholder": false,
      "reingest_program_proxy": false,
      "source_url": "https://www.indianag.org",
      "never_synthesized": true,
      "honest_labeling": true,
      "provenance": {
        "batch_block": "ta_tier3_foundation",
        "source_seed_id": "nf-seed-2026-t3-063",
        "platform_adapter_key": "foundation_html_listing",
        "empty_honest": true
      }
    },
    {
      "grant_id": "ta3-real-065",
      "source_seed_id": "nf-seed-2026-t3-065",
      "opportunity_number": "T3-065",
      "opportunity_title": "Native Voices Rising Rapid Response Fund",
      "agency": "Native Voices Rising (NDN Collective + NAP partnership)",
      "eligibility_text": "",
      "tier": 3,
      "synopsis": "Federal grant program: Native Voices Rising (NDN Collective + NAP partnership) \u2014 Native Voices Rising Rapid Response Fund. No posted NOFO on Grants.gov at ingest (no_live_nofo).",
      "tribal_eligible": false,
      "applicant_types_include_tribal": null,
      "tribal_set_aside": false,
      "tribal_priority_points": false,
      "eligibility_tags": [],
      "source_ingestion_state": "no_live_nofo",
      "no_live_nofo": true,
      "empty_honestly": true,
      "real_fetch": false,
      "fetch_mode": "no_live_nofo",
      "fixture": false,
      "search_live": true,
      "detail_live": false,
      "grants_gov_opportunity_id": null,
      "eligibility_reingest": true,
      "eligibility_reingest_diagnosis": "no_live_nofo:tier3_empty_or_apply_platform_blindspot",
      "prior_eligibility_was_placeholder": false,
      "reingest_program_proxy": false,
      "source_url": "https://nativephilanthropy.org",
      "never_synthesized": true,
      "honest_labeling": true,
      "provenance": {
        "batch_block": "ta_tier3_foundation",
        "source_seed_id": "nf-seed-2026-t3-065",
        "platform_adapter_key": "foundation_html_listing",
        "empty_honest": true
      }
    }
  ],
  "updated_at": "2026-07-01T02:55:15.896018+00:00"
}
